apolloevals/__init__.py
apolloevals-0.0.1.dist-info/METADATA
apolloevals-0.0.1.dist-info/WHEEL
apolloevals-0.0.1.dist-info/RECORD
