Metadata-Version: 2.4
Name: apolloevals
Version: 0.0.1
Summary: ApolloEvals package
Author-email: Rusheb Shah <rusheb@apolloresearch.ai>
License: MIT
Requires-Python: >=3.12
